{
  "type" : "FeatureCollection",
  "features" : [{"type":"Feature","id":2,"geometry":{"type":"Point","coordinates":[30.524731429000042,25.432160549000059]},"properties":{"OBJECTID":2,"Name":"محول كهرباء","fcode":"49","discription":"قدرة 263k"}},{"type":"Feature","id":3,"geometry":{"type":"Point","coordinates":[30.526529799000059,25.436415965000037]},"properties":{"OBJECTID":3,"Name":"محول كهرباء","fcode":"49","discription":"قدرة 263k"}},{"type":"Feature","id":4,"geometry":{"type":"Point","coordinates":[30.524761588000047,25.432935248000035]},"properties":{"OBJECTID":4,"Name":"محول كهرباء","fcode":"49","discription":"قدرة 263k"}},{"type":"Feature","id":5,"geometry":{"type":"Point","coordinates":[30.539730818000066,25.444110649000038]},"properties":{"OBJECTID":5,"Name":"محول كهرباء","fcode":"49","discription":"قدرة 263k"}},{"type":"Feature","id":6,"geometry":{"type":"Point","coordinates":[30.536735875000034,25.446276504000025]},"properties":{"OBJECTID":6,"Name":"محول كهرباء","fcode":"49","discription":"قدرة 263k"}}]
}